libcache/__init__.py
libcache-1.2.dist-info/METADATA
libcache-1.2.dist-info/WHEEL
libcache-1.2.dist-info/top_level.txt
libcache-1.2.dist-info/RECORD
